ecn_robotics/__init__.py
ecn_robotics/display.py
ecn_robotics/math.py
ecn_robotics-0.0.3.dist-info/LICENSE
ecn_robotics-0.0.3.dist-info/METADATA
ecn_robotics-0.0.3.dist-info/WHEEL
ecn_robotics-0.0.3.dist-info/top_level.txt
ecn_robotics-0.0.3.dist-info/RECORD
