Metadata-Version: 2.1
Name: ecn-robotics
Version: 0.0.3
Summary: Python package providing some utils function to analyse robots
Home-page: https://github.com/Baxterminator/ecn_robotics
Author: Geoffrey CÔTE
Author-email: geoffrey.cote@centraliens-nantes.org
License: GNU GPLv3
Keywords: robot,analysis,identification
License-File: LICENSE
Requires-Dist: numpy
Requires-Dist: colorama
